antpathmatcher/__init__.py
antpathmatcher/antpathmatcher.py
antpathmatcher/py.typed
antpathmatcher-1.0.2.dist-info/METADATA
antpathmatcher-1.0.2.dist-info/WHEEL
antpathmatcher-1.0.2.dist-info/entry_points.txt
antpathmatcher-1.0.2.dist-info/licenses/LICENSE
antpathmatcher-1.0.2.dist-info/RECORD
