Metadata-Version: 2.4
Name: antpathmatcher
Version: 1.0.2
Summary: Python Implementation of the Ant-style path patterns, inspired by Spring Framework's AntPathMatcher.
Project-URL: homepage, https://github.com/sylvainmouquet/antpathmatcher
Project-URL: documentation, https://github.com/sylvainmouquet/antpathmatcher
Project-URL: repository, https://github.com/sylvainmouquet/antpathmatcher
Project-URL: changelog, https://github.com/sylvainmouquet/antpathmatcher/releases
Author-email: Sylvain Mouquet <sylvain.mouquet@gmail.com>
License: MIT
License-File: LICENSE
Keywords: ant,matcher,path,python
Classifier: Development Status :: 5 - Production/Stable
Classifier: Framework :: Pytest
Classifier: Intended Audience :: Developers
Classifier: License :: OSI Approved :: MIT License
Classifier: Programming Language :: Python
Classifier: Programming Language :: Python :: 3
Classifier: Programming Language :: Python :: 3.10
Classifier: Programming Language :: Python :: 3.11
Classifier: Programming Language :: Python :: 3.12
Classifier: Programming Language :: Python :: 3.13
Classifier: Topic :: Software Development :: Libraries :: Python Modules
Requires-Python: >=3.10
